asyncio_tcp_messages_team_2/__init__.py
asyncio_tcp_messages_team_2/main.py
tests/__init__.py
tests/test_class.py
tests/test_correct_args.py
asyncio_tcp_messages_team_2-0.1.1.dist-info/LICENSE
asyncio_tcp_messages_team_2-0.1.1.dist-info/METADATA
asyncio_tcp_messages_team_2-0.1.1.dist-info/WHEEL
asyncio_tcp_messages_team_2-0.1.1.dist-info/top_level.txt
asyncio_tcp_messages_team_2-0.1.1.dist-info/RECORD
