Metadata-Version: 2.1
Name: asyncio-tcp-messages-team-2
Version: 0.1.1
Summary: asynchronous joke
Home-page: https://gitlab.com/python-2k2s-2022/asyncio-tasks-submissions/team-2
Author: Belligraf
Author-email: naruto.shipudet@mail.ru
License: WTFPL
Platform: UNKNOWN
Requires-Python: >=3.10
License-File: LICENSE
